MANIFEST.in
README.md
setup.py
krwlol/__init__.py
krwlol/_imports_.py
krwlol/krwlol.dev.js
krwlol/krwlol.min.js
krwlol/krwlol.py
krwlol/metadata.json
krwlol/package.json
krwlol.egg-info/PKG-INFO
krwlol.egg-info/SOURCES.txt
krwlol.egg-info/dependency_links.txt
krwlol.egg-info/top_level.txt