Metadata-Version: 1.0
Name: krwlol
Version: 0.0.1
Summary: League of legends strategies website
Home-page: UNKNOWN
Author: roosyay roos17@live.nl
Author-email: UNKNOWN
License: UNKNOWN
Platform: UNKNOWN
